customary/__init__.py
customary/urls.py
customary/api/__init__.py
customary/api/admin.py
customary/api/models.py
customary/api/views.py
customary/api/migrations/0001_initial.py
customary/api/migrations/__init__.py
customary/users/__init__.py
customary/users/admin.py
customary/users/models.py
customary/users/tests.py
customary/users/views.py
customary/users/migrations/__init__.py
django_customary-0.0.1.dev4.dist-info/DESCRIPTION.rst
django_customary-0.0.1.dev4.dist-info/METADATA
django_customary-0.0.1.dev4.dist-info/RECORD
django_customary-0.0.1.dev4.dist-info/WHEEL
django_customary-0.0.1.dev4.dist-info/metadata.json
django_customary-0.0.1.dev4.dist-info/top_level.txt
