Metadata-Version: 2.0
Name: django-customary
Version: 0.0.1.dev4
Summary: Customary Toolbox for Django
Home-page: https://github.com/precond/django-customary
Author: Juhana Räsänen
Author-email: juhana.rasanen@precond.com
License: MIT
Keywords: SME CRM application development Django
Platform: UNKNOWN
Classifier: Development Status :: 2 - Pre-Alpha
Classifier: Intended Audience :: Developers
Classifier: Topic :: Software Development :: Libraries :: Application Frameworks
Classifier: License :: OSI Approved :: MIT License
Classifier: Programming Language :: Python :: 2
Classifier: Programming Language :: Python :: 2.6
Classifier: Programming Language :: Python :: 2.7
Classifier: Programming Language :: Python :: 3
Classifier: Programming Language :: Python :: 3.2
Classifier: Programming Language :: Python :: 3.3
Classifier: Programming Language :: Python :: 3.4
Requires-Dist: django (>=1.8)
